mcp_simple_arxiv/__init__.py
mcp_simple_arxiv/__main__.py
mcp_simple_arxiv/arxiv_client.py
mcp_simple_arxiv/categories.py
mcp_simple_arxiv/server.py
mcp_simple_arxiv/taxonomy.json
mcp_simple_arxiv/update_taxonomy.py
mseep_mcp_simple_arxiv-0.3.1.dist-info/licenses/LICENSE
mseep_mcp_simple_arxiv-0.3.1.dist-info/METADATA
mseep_mcp_simple_arxiv-0.3.1.dist-info/WHEEL
mseep_mcp_simple_arxiv-0.3.1.dist-info/entry_points.txt
mseep_mcp_simple_arxiv-0.3.1.dist-info/top_level.txt
mseep_mcp_simple_arxiv-0.3.1.dist-info/RECORD
